wwolframclient/__init__.py
wwolframclient-0.0.2.dist-info/METADATA
wwolframclient-0.0.2.dist-info/WHEEL
wwolframclient-0.0.2.dist-info/top_level.txt
wwolframclient-0.0.2.dist-info/zip-safe
wwolframclient-0.0.2.dist-info/RECORD
